{
  "exchange_rate": [
    {
      "bank": "BBVA Provincial",
      "urlname": "bbva_provincial",
      "buying": 38.9012,
      "selling": 39.0784
    },
    {
      "bank": "Banesco",
      "urlname": "banesco",
      "buying": 38.9404,
      "selling": 39.0774
    },
    {
      "bank": "Banco Mercantil",
      "urlname": "banco_mercantil",
      "buying": 38.911,
      "selling": 38.9378
    },
    {
      "bank": "Banco Venezolano de Crédito",
      "urlname": "banco_venezolano_de_crédito",
      "buying": 38.9157,
      "selling": 39.0698
    },
    {
      "bank": "BCV",
      "selling": 39.0116,
      "buying": 39.0116,
      "urlname": "bcv"
    }
  ],
  "date": "2024-10-17T01:11:25.839Z",
  "source": "bcv.org.ve",
  "logo_img": "https://www.bcv.org.ve/sites/default/files/bcv5_0.ico"
}