[
  {
    "origin": "Dólar EM",
    "price": "25,67",
    "stock": "0,10  ▲ 0,39%",
    "imgUrl": "exchangemonitor"
  },
  {
    "origin": "Monitor Dolar Venezuela",
    "price": "25,73",
    "stock": "0,11  ▲ 0,43%",
    "imgUrl": "monitor-dolar"
  },
  {
    "origin": "EnParaleloVzla",
    "price": "25,64",
    "stock": "0,01  ▲ 0,04%",
    "imgUrl": "monitor-dolar"
  },
  {
    "origin": "Monitor Dolar Vzla",
    "price": "24,92",
    "stock": "0,01  ▼ 0,04%",
    "imgUrl": "monitor-dolar-vzla"
  },
  {
    "origin": "Petro",
    "price": "1.446,25",
    "stock": "0,00  0,00%",
    "imgUrl": "petro"
  },
  {
    "origin": "BCV",
    "price": "24,87",
    "stock": "0,06  ▲ 0,23%",
    "imgUrl": "bcv"
  },
  {
    "origin": "Remesas Zoom",
    "price": "25,12",
    "stock": "0,00  0,00%",
    "imgUrl": "remesas-zoom"
  },
  {
    "origin": "Italcambio",
    "price": "25,12",
    "stock": "0,00  0,00%",
    "imgUrl": "italcambio"
  },
  {
    "origin": "Bancamiga",
    "price": "24,79",
    "stock": "0,09  ▼ 0,35%",
    "imgUrl": "bancamiga"
  },
  {
    "origin": "BanCaribe",
    "price": "17,26",
    "stock": "0,00  0,00%",
    "imgUrl": "bancaribe"
  },
  {
    "origin": "Banco de Venezuela",
    "price": "24,36",
    "stock": "0,00  0,00%",
    "imgUrl": "banco-de-venezuela"
  },
  {
    "origin": "Banco Exterior",
    "price": "25,12",
    "stock": "1,01  ▲ 4,18%",
    "imgUrl": "banco-exterior"
  },
  {
    "origin": "Banplus",
    "price": "24,56",
    "stock": "0,00  0,00%",
    "imgUrl": "banplus"
  },
  {
    "origin": "BNC",
    "price": "24,81",
    "stock": "0,03  ▲ 0,14%",
    "imgUrl": "bnc"
  },
  {
    "origin": "Banesco",
    "price": "25,22",
    "stock": "0,41  ▲ 1,64%",
    "imgUrl": "banesco"
  },
  {
    "origin": "BBVA Provincial",
    "price": "24,73",
    "stock": "0,00  0,00%",
    "imgUrl": "bbva-provincial"
  },
  {
    "origin": "Mercantil",
    "price": "24,86",
    "stock": "0,00  0,00%",
    "imgUrl": "mercantil"
  },
  {
    "origin": "Otras Instituciones",
    "price": "24,99",
    "stock": "0,25  ▲ 1,02%",
    "imgUrl": "otras-instituciones"
  },
  {
    "origin": "Binance",
    "price": "25,53",
    "stock": "0,07  ▼ 0,27%",
    "imgUrl": "binance"
  },
  {
    "origin": "LocalBitcoins",
    "price": "25,79",
    "stock": "0,46  ▼ 1,75%",
    "imgUrl": "localbitcoins"
  },
  {
    "origin": "AirTM",
    "price": "26,38",
    "stock": "0,12  ▲ 0,46%",
    "imgUrl": "airtm"
  },
  {
    "origin": "Reserve",
    "price": "26,07",
    "stock": "0,14  ▲ 0,54%",
    "imgUrl": "reserve"
  },
  {
    "origin": "Yadio",
    "price": "25,35",
    "stock": "0,02  ▲ 0,08%",
    "imgUrl": "yadio"
  },
  {
    "origin": "DolarToday",
    "price": "25,65",
    "stock": "0,10  ▲ 0,39%",
    "imgUrl": "dolartoday"
  },
  {
    "origin": "DolarToday (BTC)",
    "price": "25,61",
    "stock": "0,11  ▲ 0,43%",
    "imgUrl": "dolartoday-btc"
  },
  {
    "origin": "Mkambio",
    "price": "25,65",
    "stock": "0,50  ▲ 1,99%",
    "imgUrl": "mkambio"
  },
  {
    "origin": "Cambios R&A",
    "price": "25,72",
    "stock": "0,02  ▲ 0,08%",
    "imgUrl": "cambios-rya"
  },
  {
    "origin": "PayPal",
    "price": "22,60",
    "stock": "0,10  ▲ 0,44%",
    "imgUrl": "paypal"
  },
  {
    "origin": "Zinli",
    "price": "23,40",
    "stock": "0,10  ▲ 0,43%",
    "imgUrl": "zinli"
  },
  {
    "origin": "Skrill",
    "price": "23,40",
    "stock": "0,10  ▲ 0,43%",
    "imgUrl": "skrill"
  },
  {
    "origin": "Amazon Gift Card",
    "price": "22,10",
    "stock": "0,10  ▲ 0,45%",
    "imgUrl": "amazon"
  }
]