{
  "exchange_rate": [
    {
      "bank": "Banesco",
      "urlname": "banesco",
      "buying": 47.9365,
      "selling": 48.0621
    },
    {
      "bank": "BBVA Provincial",
      "urlname": "bbva_provincial",
      "buying": 48.1624,
      "selling": 48.6905
    },
    {
      "bank": "Banco Mercantil",
      "urlname": "banco_mercantil",
      "buying": 48.811,
      "selling": 48.9461
    },
    {
      "bank": "Banco Activo",
      "urlname": "banco_activo",
      "buying": 48.0838,
      "selling": 49.6735
    },
    {
      "bank": "BCV",
      "selling": 48.3265,
      "buying": 48.3265,
      "urlname": "bcv"
    }
  ],
  "date": "2024-12-06T01:17:24.805Z",
  "source": "bcv.org.ve",
  "logo_img": "https://www.bcv.org.ve/sites/default/files/bcv5_0.ico"
}